bmicro/BGThread.py
bmicro/__init__.py
bmicro/__main__.py
bmicro/_version.py
bmicro/_version_save.py
bmicro/gui/__init__.py
bmicro/gui/batch_evaluation.ui
bmicro/gui/export_configuration.ui
bmicro/gui/main.py
bmicro/gui/main.ui
bmicro/gui/mpl.py
bmicro/gui/calibration/__init__.py
bmicro/gui/calibration/calibration_options.ui
bmicro/gui/calibration/calibration_view.py
bmicro/gui/calibration/calibration_view.ui
bmicro/gui/data/__init__.py
bmicro/gui/data/data_view.py
bmicro/gui/data/data_view.ui
bmicro/gui/evaluation/__init__.py
bmicro/gui/evaluation/evaluation_view.py
bmicro/gui/evaluation/evaluation_view.ui
bmicro/gui/evaluation/spectrum_view.ui
bmicro/gui/extraction/__init__.py
bmicro/gui/extraction/extraction_view.py
bmicro/gui/extraction/extraction_view.ui
bmicro/gui/peak_selection/__init__.py
bmicro/gui/peak_selection/peak_selection_view.py
bmicro/gui/peak_selection/peak_selection_view.ui
bmicro/img/icon.png
bmicro-0.11.0.dist-info/licenses/LICENSE
bmicro-0.11.0.dist-info/METADATA
bmicro-0.11.0.dist-info/WHEEL
bmicro-0.11.0.dist-info/top_level.txt
bmicro-0.11.0.dist-info/RECORD
