Metadata-Version: 2.4
Name: bmicro
Version: 0.11.0
Summary: GUI for Brillouin evaluation
Home-page: https://github.com/BrillouinMicroscopy/BMicro
Author: BMicro developers
Author-email: dev@craban.de
License: GPL v3
Keywords: Brillouin Microscopy
Platform: ALL
Classifier: Operating System :: OS Independent
Classifier: Programming Language :: Python :: 3
Classifier: Topic :: Scientific/Engineering :: Visualization
Classifier: Intended Audience :: Science/Research
Requires-Python: >=3.10
License-File: LICENSE
Requires-Dist: bmlab>=0.11.0a0
Requires-Dist: h5py>=2.10.0
Requires-Dist: matplotlib
Requires-Dist: numpy>=1.17.0
Requires-Dist: pyqt6>=6.6.0
Requires-Dist: pyqt6-qt6>=6.6.0
Requires-Dist: pytest
Requires-Dist: pytest-qt
Requires-Dist: pytest_mock
Requires-Dist: scikit-image
Requires-Dist: scipy
Dynamic: author
Dynamic: author-email
Dynamic: classifier
Dynamic: description
Dynamic: home-page
Dynamic: keywords
Dynamic: license
Dynamic: license-file
Dynamic: platform
Dynamic: requires-dist
Dynamic: requires-python
Dynamic: summary
